{
  "buildFiles": [
    "C:\\Users\\Stolid\\flutter\\3.29.2\\packages\\flutter_tools\\gradle\\src\\main\\groovy\\CMakeLists.txt"
  ],
  "cleanCommandsComponents": [
    [
      "E:\\AndroidStudioSDK\\cmake\\3.22.1\\bin\\ninja.exe",
      "-C",
      "F:\\Projects\\Python\\Learning\\Flet\\SendCoordinate\\build\\flutter\\android\\app\\.cxx\\RelWithDebInfo\\3w4q446r\\armeabi-v7a",
      "clean"
    ]
  ],
  "buildTargetsCommandComponents": [
    "E:\\AndroidStudioSDK\\cmake\\3.22.1\\bin\\ninja.exe",
    "-C",
    "F:\\Projects\\Python\\Learning\\Flet\\SendCoordinate\\build\\flutter\\android\\app\\.cxx\\RelWithDebInfo\\3w4q446r\\armeabi-v7a",
    "{LIST_OF_TARGETS_TO_BUILD}"
  ],
  "libraries": {},
  "toolchains": {
    "toolchain": {
      "cCompilerExecutable": "E:\\AndroidStudioSDK\\ndk\\27.0.12077973\\toolchains\\llvm\\prebuilt\\windows-x86_64\\bin\\clang.exe",
      "cppCompilerExecutable": "E:\\AndroidStudioSDK\\ndk\\27.0.12077973\\toolchains\\llvm\\prebuilt\\windows-x86_64\\bin\\clang++.exe"
    }
  },
  "cFileExtensions": [],
  "cppFileExtensions": []
}